cooper_pair/__init__.py
cooper_pair/pair.py
cooper_pair/version.py
tests/__init__.py
tests/test_pair.py
cooper_pair-0.0.4.dist-info/LICENSE
cooper_pair-0.0.4.dist-info/METADATA
cooper_pair-0.0.4.dist-info/WHEEL
cooper_pair-0.0.4.dist-info/top_level.txt
cooper_pair-0.0.4.dist-info/RECORD
