Metadata-Version: 2.1
Name: cooper-pair
Version: 0.0.4
Summary: A small library that provides programmatic access to Superconductive's GraphQL API.
Home-page: https://github.com/superconductive/cooper-pair
Author: Superconductive Health
Author-email: dev@superconductivehealth.com
Maintainer: Superconductive Health
Maintainer-email: dev@superconductivehealth.com
License: UNKNOWN
Platform: UNKNOWN
Classifier: Programming Language :: Python :: 3
Classifier: License :: OSI Approved :: Apache Software License
Classifier: Operating System :: OS Independent
Requires-Dist: gql
Requires-Dist: requests
Requires-Dist: great-expectations
